{
    "week01" : [ "week01/chamber-site-plan.html"],

    "week02" : [ "week02/design.html",
                 "week02/bom.html",
                 "https://codepen.io/mhill07/pen/BaPZKqM",
                 "chamber/index.html"],

    "week03" : [ "week03/images/landscape.webp", 
                 "week03/lazyload.html", 
                 "https://codepen.io/mhill07/pen/JjBMjRG", 
                 "week03/bom.html", 
                 "chamber/discover.html"],
            
    "week04" : [ "https://codepen.io/mhill07/pen/bGjKdwZ", 
                 "images/week04activity.png", 
                 "week04/tablebuild.html", 
                 "week04/form-start/index.html", 
                 "chamber/join.html"],

    "week05" : [ "https://codepen.io/mhill07/pen/xxJmMGJ", 
                 "week05/new-ward-members.json", 
                 "week05/prophets.html", 
                 "week05/weather.html"]
}